{
    "empleado": "admin",
    "fecha_creacion": "2025-05-04T21:23:58.959750+00:00",
    "estado": "PENDIENTE",
    "observaciones": "rapidamente urgente",
    "detalles": [
        {
            "zapato_id": "AP40NHA0001,AP40NHA0002,AP40NHA0003,AP40NHA0004,AP40NHA0005,AP40NHA0006,AP40NHA0007,AP40NHA0008,AP40NHA0009,AP40NHA0010,AP40NHA0011,AP40NHA0012,AP40NHA0013,AP40NHA0014,AP40NHA0015,AP40NHA0016,AP40NHA0017,AP40NHA0018,AP40NHA0019,AP40NHA0020,AP40NHA0021",
            "modelo": "Apache Hombre",
            "talla": "40",
            "sexo": "H",
            "color": "Negro",
            "cantidad": 21,
            "imagen": "images/ApacheH1.png"
        },
        {
            "zapato_id": "AM36NHC0001",
            "modelo": "Amaka Hombre",
            "talla": "36",
            "sexo": "H",
            "color": "Negro",
            "cantidad": 1,
            "imagen": "images/AmakaH3.png"
        },
        {
            "zapato_id": "AM36NHA0001,AM36NHA0002,AM36NHA0003,AM36NHA0004,AM36NHA0005,AM36NHA0006,AM36NHA0007,AM36NHA0008",
            "modelo": "Amaka Hombre",
            "talla": "36",
            "sexo": "H",
            "color": "Negro",
            "cantidad": 8,
            "imagen": "images/AmakaH1.png"
        }
    ]
}